evalsync/__init__.py
evalsync/cli.py
evalsync/manager.py
evalsync/py.typed
evalsync/worker.py
evalsync/aio/__init__.py
evalsync/aio/manager.py
evalsync/async/__init__.py
evalsync/async/manager.py
evalsync/proto/sync_pb2.py
evalsync/proto/sync_pb2.pyi
evalsync-0.7.0.dist-info/METADATA
evalsync-0.7.0.dist-info/WHEEL
evalsync-0.7.0.dist-info/entry_points.txt
evalsync-0.7.0.dist-info/RECORD
