Metadata-Version: 2.4
Name: evalsync
Version: 0.7.0
Summary: evalsync is a library used to synchronize applications under benchmark with an external manager
Author-email: minhuw <wangmh15@gmail.com>
Requires-Python: >=3.10
Requires-Dist: jinja2>=3.1.5
Requires-Dist: loguru>=0.7.3
Requires-Dist: protobuf>=6.33.1
Requires-Dist: pyzmq>=27.1.0
Requires-Dist: typer>=0.20.0
